splatpy2/__init__.py
splatpy2/auth.py
splatpy2/utils.py
splatpy2-0.1.0a0.dist-info/LICENSE
splatpy2-0.1.0a0.dist-info/METADATA
splatpy2-0.1.0a0.dist-info/WHEEL
splatpy2-0.1.0a0.dist-info/top_level.txt
splatpy2-0.1.0a0.dist-info/zip-safe
splatpy2-0.1.0a0.dist-info/RECORD
