Metadata-Version: 2.1
Name: splatpy2
Version: 0.1.0a0
Summary: A lightweight Python SDK for the Splatoon2 Web API.
Home-page: https://github.com/sp-yduck/splatpy2
Author: Teppei Sudo
Author-email: sudo20.t.ab@gmail.com
License: MIT
Platform: UNKNOWN
Classifier: Programming Language :: Python :: 3
License-File: LICENSE
